save_return/__init__.py
save_return-0.2.0.dist-info/METADATA
save_return-0.2.0.dist-info/WHEEL
save_return-0.2.0.dist-info/RECORD
