Metadata-Version: 2.3
Name: save-return
Version: 0.2.0
Summary: Save the return value of the decorated function to a versioned pickle file
Project-URL: Homepage, https://github.com/qwfy/save_return
Project-URL: Documentation, https://github.com/qwfy/save_return
Project-URL: Repository, https://github.com/qwfy/save_return
Author-email: incomplete <incomplete@aixon.co>
Requires-Python: >=3.8
